{
  "date": "2026-07-08",
  "generated_at": "2026-07-08T16:10:29",
  "sections": {
    "ai": {
      "label": "AI 뉴스 점수 픽",
      "updated_at": "2026-07-08T16:10:29",
      "pick_date": "2026-07-08",
      "count": 1,
      "picks": [
        {
          "stock_code": "024110",
          "name_kr": "기업은행",
          "ms_score": 62,
          "ai_score": 63,
          "confidence": "MEDIUM",
          "reason": "분기 배당 신규 도입이라는 구조적 주주환원 강화 재료는 '수급_개선' 패턴에 해당하며, 과거 2026-07-03 동일 종목 +3.40% 성공 사례와 유사한 환경입니다. RSI 44로 중립 구간에 위치해 과매수 부담이 없고, 배당 정책 본격화에 따른 점진적 재평가 기대가 유효합니다.",
          "entry_price": 21350.0
        }
      ],
      "accuracy": {
        "total": 107,
        "correct": 49,
        "hit_rate": 45.8,
        "avg_return": 0.25,
        "avg_return_open": 0.72,
        "yesterday_date": "2026-07-07",
        "yesterday": [
          {
            "stock_code": "030200",
            "name_kr": "KT",
            "entry_price": 54500.0,
            "exit_price": 55500.0,
            "return_pct": 1.83,
            "return_pct_open": 1.83,
            "correct": 1
          },
          {
            "stock_code": "010140",
            "name_kr": "삼성중공업",
            "entry_price": 23700.0,
            "exit_price": 22450.0,
            "return_pct": -5.27,
            "return_pct_open": -5.27,
            "correct": 0
          }
        ]
      }
    },
    "hybrid": {
      "label": "실적·기술 하이브리드",
      "updated_at": "2026-07-08T16:10:29",
      "pick_date": "2026-07-08",
      "count": 5,
      "picks": [
        {
          "stock_code": "005490",
          "name_kr": "POSCO홀딩스",
          "ms_score": 55,
          "ai_score": 98,
          "confidence": "HIGH",
          "reason": "[E] tech 41 / earn 98 (RSI 32, 5일 +0.2%)",
          "entry_price": 315500.0
        },
        {
          "stock_code": "010140",
          "name_kr": "삼성중공업",
          "ms_score": 73,
          "ai_score": 78,
          "confidence": "MEDIUM",
          "reason": "[T] tech 79 / earn 0 (RSI 26, 5일 -5.5%)",
          "entry_price": 22450.0
        },
        {
          "stock_code": "068270",
          "name_kr": "셀트리온",
          "ms_score": 67,
          "ai_score": 78,
          "confidence": "MEDIUM",
          "reason": "[E] tech 0 / earn 79 (RSI 53, 5일 +2.1%)",
          "entry_price": 178200.0
        },
        {
          "stock_code": "047050",
          "name_kr": "포스코인터내셔널",
          "ms_score": 64,
          "ai_score": 76,
          "confidence": "MEDIUM",
          "reason": "[T] tech 76 / earn 69 (RSI 37, 5일 -3.1%)",
          "entry_price": 49700.0
        },
        {
          "stock_code": "003550",
          "name_kr": "LG",
          "ms_score": 58,
          "ai_score": 47,
          "confidence": "LOW",
          "reason": "[T] tech 48 / earn 0 (RSI 36, 5일 +5.9%)",
          "entry_price": 102300.0
        }
      ],
      "accuracy": {
        "total": 135,
        "correct": 62,
        "hit_rate": 45.9,
        "avg_return": -0.26,
        "avg_return_open": 0.06,
        "yesterday_date": "2026-07-07",
        "yesterday": [
          {
            "stock_code": "068270",
            "name_kr": "셀트리온",
            "entry_price": 175900.0,
            "exit_price": 178200.0,
            "return_pct": 1.31,
            "return_pct_open": 1.31,
            "correct": 1
          },
          {
            "stock_code": "047050",
            "name_kr": "포스코인터내셔널",
            "entry_price": 50000.0,
            "exit_price": 49700.0,
            "return_pct": -0.6,
            "return_pct_open": -0.6,
            "correct": 0
          },
          {
            "stock_code": "006400",
            "name_kr": "삼성SDI",
            "entry_price": 451500.0,
            "exit_price": 445000.0,
            "return_pct": -1.44,
            "return_pct_open": -1.44,
            "correct": 0
          },
          {
            "stock_code": "005490",
            "name_kr": "POSCO홀딩스",
            "entry_price": 321500.0,
            "exit_price": 315500.0,
            "return_pct": -1.87,
            "return_pct_open": -1.87,
            "correct": 0
          },
          {
            "stock_code": "032830",
            "name_kr": "삼성생명",
            "entry_price": 393500.0,
            "exit_price": 375000.0,
            "return_pct": -4.7,
            "return_pct_open": -4.7,
            "correct": 0
          }
        ]
      }
    },
    "vol": {
      "label": "거래대금 2000억 돌파",
      "updated_at": "2026-07-08T16:10:29",
      "pick_date": "2026-07-08",
      "count": 0,
      "picks": [],
      "watching": [],
      "holding": [],
      "history": [],
      "initial_capital": 2000000,
      "slots": 5,
      "slot_size": 400000,
      "month_return": 0.0,
      "month_count": 0,
      "month_pnl": 0,
      "month_start": "2026-07-01",
      "year_return": 0.0,
      "year_count": 0,
      "year_pnl": 0,
      "year_start": "2026-01-01",
      "accuracy": null
    }
  }
}
